odoo9_addon_website_form_metadata-9.0.1.0.0-py2.7-nspkg.pth
odoo9_addon_website_form_metadata-9.0.1.0.0.dist-info/DESCRIPTION.rst
odoo9_addon_website_form_metadata-9.0.1.0.0.dist-info/METADATA
odoo9_addon_website_form_metadata-9.0.1.0.0.dist-info/RECORD
odoo9_addon_website_form_metadata-9.0.1.0.0.dist-info/WHEEL
odoo9_addon_website_form_metadata-9.0.1.0.0.dist-info/metadata.json
odoo9_addon_website_form_metadata-9.0.1.0.0.dist-info/namespace_packages.txt
odoo9_addon_website_form_metadata-9.0.1.0.0.dist-info/top_level.txt
odoo_addons/website_form_metadata/README.rst
odoo_addons/website_form_metadata/__init__.py
odoo_addons/website_form_metadata/__openerp__.py
odoo_addons/website_form_metadata/models/__init__.py
odoo_addons/website_form_metadata/models/website_config_settings.py
odoo_addons/website_form_metadata/views/res_config_view.xml
